{"item":[{"name":"v1","description":"","item":[{"name":"chess","description":"","item":[{"name":"openings","description":"","item":[{"id":"e531dffb-a4f6-4aec-a786-ccaf51d81182","name":"Openings Controller get Openings","request":{"name":"Openings Controller get Openings","description":{},"url":{"path":["v1","chess","openings"],"host":["{{baseUrl}}"],"query":[{"disabled":false,"description":{"content":"offset","type":"text/plain"},"key":"offset","value":"<number>"},{"disabled":false,"description":{"content":"limit","type":"text/plain"},"key":"limit","value":"<number>"},{"disabled":false,"description":{"content":"name","type":"text/plain"},"key":"name","value":"<string>"},{"disabled":false,"description":{"content":"eco","type":"text/plain"},"key":"eco","value":"<string>"}],"variable":[]},"header":[{"key":"Accept","value":"application/json"}],"method":"GET","body":{},"auth":null},"response":[{"id":"43b03fbc-225b-4b40-9c03-a03cde640336","originalRequest":{"url":{"path":["v1","chess","openings"],"host":["{{baseUrl}}"],"query":[{"disabled":false,"description":{"content":"offset","type":"text/plain"},"key":"offset","value":"<number>"},{"disabled":false,"description":{"content":"limit","type":"text/plain"},"key":"limit","value":"<number>"},{"disabled":false,"description":{"content":"name","type":"text/plain"},"key":"name","value":"<string>"},{"disabled":false,"description":{"content":"eco","type":"text/plain"},"key":"eco","value":"<string>"}],"variable":[]},"header":[{"key":"Accept","value":"application/json"}],"method":"GET","body":{}},"status":"OK","code":200,"header":[{"key":"Content-Type","value":"application/json"}],"body":"{\n  \"total\": \"<number>\",\n  \"openings\": []\n}","cookie":[],"_postman_previewlanguage":"json"}],"event":[],"protocolProfileBehavior":{"disableBodyPruning":true}},{"name":"ecos","description":"","item":[{"id":"ae46c6a2-2aed-4ee8-94c1-6be1e8b2d8ca","name":"Openings Controller get EC Os","request":{"name":"Openings Controller get EC Os","description":{},"url":{"path":["v1","chess","openings","ecos"],"host":["{{baseUrl}}"],"query":[],"variable":[]},"header":[{"key":"Accept","value":"application/json"}],"method":"GET","body":{},"auth":null},"response":[{"id":"2cff37ae-ccb4-409f-a47e-477b553017a4","originalRequest":{"url":{"path":["v1","chess","openings","ecos"],"host":["{{baseUrl}}"],"query":[],"variable":[]},"header":[{"key":"Accept","value":"application/json"}],"method":"GET","body":{}},"status":"OK","code":200,"header":[{"key":"Content-Type","value":"application/json"}],"body":"{\n  \"total\": \"<number>\",\n  \"ecos\": [\n    \"<string>\",\n    \"<string>\"\n  ]\n}","cookie":[],"_postman_previewlanguage":"json"}],"event":[],"protocolProfileBehavior":{"disableBodyPruning":true}}]}]},{"name":"players","description":"","item":[{"id":"857f50ce-8a2a-4277-9e15-cc5ed75f0303","name":"Player Controller get Players","request":{"name":"Player Controller get Players","description":{},"url":{"path":["v1","chess","players"],"host":["{{baseUrl}}"],"query":[{"disabled":false,"description":{"content":"limit","type":"text/plain"},"key":"limit","value":"<number>"},{"disabled":false,"description":{"content":"offset","type":"text/plain"},"key":"offset","value":"<number>"}],"variable":[]},"header":[{"key":"Accept","value":"application/json"}],"method":"GET","body":{},"auth":null},"response":[{"id":"31197aab-5c04-4dba-952c-f527637effda","originalRequest":{"url":{"path":["v1","chess","players"],"host":["{{baseUrl}}"],"query":[{"disabled":false,"description":{"content":"limit","type":"text/plain"},"key":"limit","value":"<number>"},{"disabled":false,"description":{"content":"offset","type":"text/plain"},"key":"offset","value":"<number>"}],"variable":[]},"header":[{"key":"Accept","value":"application/json"}],"method":"GET","body":{}},"status":"OK","code":200,"header":[{"key":"Content-Type","value":"application/json"}],"body":"{\n  \"total\": \"<number>\",\n  \"players\": []\n}","cookie":[],"_postman_previewlanguage":"json"}],"event":[],"protocolProfileBehavior":{"disableBodyPruning":true}},{"name":"{username}","description":"","item":[{"id":"9e9c4811-d1b3-41ca-9120-88ff60a86158","name":"Player Controller get Player","request":{"name":"Player Controller get Player","description":{},"url":{"path":["v1","chess","players",":username"],"host":["{{baseUrl}}"],"query":[],"variable":[{"type":"any","value":"<string>","key":"username","disabled":false,"description":{"content":"(Required) ","type":"text/plain"}}]},"header":[{"key":"Accept","value":"application/json"}],"method":"GET","body":{},"auth":null},"response":[{"id":"a0158cdc-69af-4b5c-b841-5b84b3be6cf2","originalRequest":{"url":{"path":["v1","chess","players",":username"],"host":["{{baseUrl}}"],"query":[],"variable":[]},"header":[{"key":"Accept","value":"application/json"}],"method":"GET","body":{}},"status":"OK","code":200,"header":[{"key":"Content-Type","value":"application/json"}],"body":"{}","cookie":[],"_postman_previewlanguage":"json"}],"event":[],"protocolProfileBehavior":{"disableBodyPruning":true}},{"id":"b863a686-bdf2-4eb7-ba91-169e669b8445","name":"Player Controller sync Player","request":{"name":"Player Controller sync Player","description":{},"url":{"path":["v1","chess","players",":username"],"host":["{{baseUrl}}"],"query":[],"variable":[{"type":"any","value":"<string>","key":"username","disabled":false,"description":{"content":"(Required) ","type":"text/plain"}}]},"header":[{"key":"Accept","value":"application/json"}],"method":"POST","body":{},"auth":null},"response":[{"id":"af4b1af8-9d68-4127-a6c5-fd6ec4dd78ce","originalRequest":{"url":{"path":["v1","chess","players",":username"],"host":["{{baseUrl}}"],"query":[],"variable":[]},"header":[{"key":"Accept","value":"application/json"}],"method":"POST","body":{}},"status":"OK","code":200,"header":[{"key":"Content-Type","value":"application/json"}],"body":"{}","cookie":[],"_postman_previewlanguage":"json"}],"event":[],"protocolProfileBehavior":{"disableBodyPruning":true}},{"name":"games","description":"","item":[{"id":"3d77772e-a9ee-4db6-829e-a097eed38f49","name":"Games Controller get Games","request":{"name":"Games Controller get Games","description":{},"url":{"path":["v1","chess","players",":username","games"],"host":["{{baseUrl}}"],"query":[{"disabled":false,"description":{"content":"year","type":"text/plain"},"key":"year","value":"<number>"},{"disabled":false,"description":{"content":"month","type":"text/plain"},"key":"month","value":"<number>"},{"disabled":false,"description":{"content":"limit","type":"text/plain"},"key":"limit","value":"<number>"},{"disabled":false,"description":{"content":"offset","type":"text/plain"},"key":"offset","value":"<number>"}],"variable":[{"type":"any","value":"<string>","key":"username","disabled":false,"description":{"content":"(Required) username","type":"text/plain"}}]},"header":[{"key":"Accept","value":"application/json"}],"method":"GET","body":{},"auth":null},"response":[{"id":"6f15f2ce-bcb0-4363-adc9-e063bbfd6ea0","originalRequest":{"url":{"path":["v1","chess","players",":username","games"],"host":["{{baseUrl}}"],"query":[{"disabled":false,"description":{"content":"year","type":"text/plain"},"key":"year","value":"<number>"},{"disabled":false,"description":{"content":"month","type":"text/plain"},"key":"month","value":"<number>"},{"disabled":false,"description":{"content":"limit","type":"text/plain"},"key":"limit","value":"<number>"},{"disabled":false,"description":{"content":"offset","type":"text/plain"},"key":"offset","value":"<number>"}],"variable":[]},"header":[{"key":"Accept","value":"application/json"}],"method":"GET","body":{}},"status":"OK","code":200,"header":[{"key":"Content-Type","value":"application/json"}],"body":"{\n  \"total\": \"<number>\",\n  \"games\": []\n}","cookie":[],"_postman_previewlanguage":"json"}],"event":[],"protocolProfileBehavior":{"disableBodyPruning":true}},{"id":"9173b6fd-4683-4a88-b0ff-4070cbfeca0e","name":"Games Controller sync Games","request":{"name":"Games Controller sync Games","description":{},"url":{"path":["v1","chess","players",":username","games"],"host":["{{baseUrl}}"],"query":[],"variable":[{"type":"any","value":"<string>","key":"username","disabled":false,"description":{"content":"(Required) ","type":"text/plain"}}]},"header":[{"key":"Content-Type","value":"application/json"},{"key":"Accept","value":"application/json"}],"method":"POST","body":{"mode":"raw","raw":"{\n  \"month\": \"<number>\",\n  \"year\": \"<number>\"\n}","options":{"raw":{"headerFamily":"json","language":"json"}}},"auth":null},"response":[{"id":"a36de473-ec20-417e-922c-fb5a4c7dc526","originalRequest":{"url":{"path":["v1","chess","players",":username","games"],"host":["{{baseUrl}}"],"query":[],"variable":[]},"header":[{"key":"Content-Type","value":"application/json"},{"key":"Accept","value":"application/json"}],"method":"POST","body":{"mode":"raw","raw":"{\n  \"month\": \"<number>\",\n  \"year\": \"<number>\"\n}","options":{"raw":{"headerFamily":"json","language":"json"}}}},"status":"OK","code":200,"header":[{"key":"Content-Type","value":"application/json"}],"body":"{\n  \"total\": \"<number>\",\n  \"synced\": \"<number>\",\n  \"existed\": \"<number>\"\n}","cookie":[],"_postman_previewlanguage":"json"}],"event":[],"protocolProfileBehavior":{"disableBodyPruning":true}},{"name":"{gameId}","description":"","item":[{"id":"9db8612b-6312-48e8-8d8b-b63256c13896","name":"Games Controller get Game","request":{"name":"Games Controller get Game","description":{},"url":{"path":["v1","chess","players",":username","games",":gameId"],"host":["{{baseUrl}}"],"query":[],"variable":[{"type":"any","value":"<string>","key":"username","disabled":false,"description":{"content":"(Required) ","type":"text/plain"}},{"type":"any","value":"<string>","key":"gameId","disabled":false,"description":{"content":"(Required) ","type":"text/plain"}}]},"header":[{"key":"Accept","value":"application/json"}],"method":"GET","body":{},"auth":null},"response":[{"id":"0e4741b3-aaed-4482-8e97-e930d002af48","originalRequest":{"url":{"path":["v1","chess","players",":username","games",":gameId"],"host":["{{baseUrl}}"],"query":[],"variable":[]},"header":[{"key":"Accept","value":"application/json"}],"method":"GET","body":{}},"status":"OK","code":200,"header":[{"key":"Content-Type","value":"application/json"}],"body":"{}","cookie":[],"_postman_previewlanguage":"json"}],"event":[],"protocolProfileBehavior":{"disableBodyPruning":true}},{"name":"pgn","description":"","item":[{"id":"eb3f009e-0f57-4149-a08d-89d2b8fca3ac","name":"Games Controller get Game PGN","request":{"name":"Games Controller get Game PGN","description":{},"url":{"path":["v1","chess","players",":username","games",":gameId","pgn"],"host":["{{baseUrl}}"],"query":[],"variable":[{"type":"any","value":"<string>","key":"username","disabled":false,"description":{"content":"(Required) ","type":"text/plain"}},{"type":"any","value":"<string>","key":"gameId","disabled":false,"description":{"content":"(Required) ","type":"text/plain"}}]},"header":[{"key":"Accept","value":"application/json"}],"method":"GET","body":{},"auth":null},"response":[{"id":"cbde7ff4-bcb2-4c08-8d3e-a2807c736d76","originalRequest":{"url":{"path":["v1","chess","players",":username","games",":gameId","pgn"],"host":["{{baseUrl}}"],"query":[],"variable":[]},"header":[{"key":"Accept","value":"application/json"}],"method":"GET","body":{}},"status":"OK","code":200,"header":[{"key":"Content-Type","value":"application/json"}],"body":"<string>","cookie":[],"_postman_previewlanguage":"json"}],"event":[],"protocolProfileBehavior":{"disableBodyPruning":true}}]}]}]},{"name":"insights","description":"","item":[{"id":"98a43147-34a3-4d7e-95b5-c5ac68d082ed","name":"Insights Controller get Insights","request":{"name":"Insights Controller get Insights","description":{},"url":{"path":["v1","chess","players",":username","insights"],"host":["{{baseUrl}}"],"query":[],"variable":[{"type":"any","value":"<string>","key":"username","disabled":false,"description":{"content":"(Required) ","type":"text/plain"}}]},"header":[{"key":"Accept","value":"application/json"}],"method":"GET","body":{},"auth":null},"response":[{"id":"bf359569-08f5-48c9-b4c4-2796dd98ae18","originalRequest":{"url":{"path":["v1","chess","players",":username","insights"],"host":["{{baseUrl}}"],"query":[],"variable":[]},"header":[{"key":"Accept","value":"application/json"}],"method":"GET","body":{}},"status":"OK","code":200,"header":[{"key":"Content-Type","value":"application/json"}],"body":"{\n  \"username\": \"<string>\",\n  \"games\": {\n    \"total\": \"<number>\",\n    \"win\": \"<number>\",\n    \"draw\": \"<number>\",\n    \"loss\": \"<number>\",\n    \"periods\": [\n      \"<string>\",\n      \"<string>\"\n    ],\n    \"timeOfDays\": [\n      \"<string>\",\n      \"<string>\"\n    ],\n    \"daysOfWeek\": [\n      \"<string>\",\n      \"<string>\"\n    ]\n  },\n  \"accuracy\": {\n    \"average\": \"<number>\",\n    \"win\": \"<number>\",\n    \"draw\": \"<number>\",\n    \"loss\": \"<number>\",\n    \"periods\": {\n      \"average\": \"<number>\",\n      \"period\": \"<number>\"\n    },\n    \"timeOfDays\": {\n      \"average\": \"<number>\",\n      \"timeOfDay\": \"<string>\"\n    },\n    \"daysOfWeek\": {\n      \"average\": \"<number>\",\n      \"dayOfWeek\": \"<string>\"\n    }\n  },\n  \"results\": {},\n  \"opponents\": [\n    {\n      \"opponent\": \"<string>\",\n      \"games\": \"<number>\",\n      \"win\": \"<number>\",\n      \"draw\": \"<number>\",\n      \"loss\": \"<number>\"\n    },\n    {\n      \"opponent\": \"<string>\",\n      \"games\": \"<number>\",\n      \"win\": \"<number>\",\n      \"draw\": \"<number>\",\n      \"loss\": \"<number>\"\n    }\n  ]\n}","cookie":[],"_postman_previewlanguage":"json"}],"event":[],"protocolProfileBehavior":{"disableBodyPruning":true}},{"name":"games","description":"","item":[{"id":"d2342022-2dc8-4b13-bfa7-144d2a8c54fa","name":"Insights Controller get Games Insights","request":{"name":"Insights Controller get Games Insights","description":{},"url":{"path":["v1","chess","players",":username","insights","games"],"host":["{{baseUrl}}"],"query":[],"variable":[{"type":"any","value":"<string>","key":"username","disabled":false,"description":{"content":"(Required) ","type":"text/plain"}}]},"header":[{"key":"Accept","value":"application/json"}],"method":"GET","body":{},"auth":null},"response":[{"id":"c1d076fb-e648-44d5-bec9-d7fbeb5cfb68","originalRequest":{"url":{"path":["v1","chess","players",":username","insights","games"],"host":["{{baseUrl}}"],"query":[],"variable":[]},"header":[{"key":"Accept","value":"application/json"}],"method":"GET","body":{}},"status":"OK","code":200,"header":[{"key":"Content-Type","value":"application/json"}],"body":"{\n  \"username\": \"<string>\",\n  \"games\": {\n    \"total\": \"<number>\",\n    \"win\": \"<number>\",\n    \"draw\": \"<number>\",\n    \"loss\": \"<number>\",\n    \"periods\": [\n      \"<string>\",\n      \"<string>\"\n    ],\n    \"timeOfDays\": [\n      \"<string>\",\n      \"<string>\"\n    ],\n    \"daysOfWeek\": [\n      \"<string>\",\n      \"<string>\"\n    ]\n  },\n  \"accuracy\": {\n    \"average\": \"<number>\",\n    \"win\": \"<number>\",\n    \"draw\": \"<number>\",\n    \"loss\": \"<number>\",\n    \"periods\": {\n      \"average\": \"<number>\",\n      \"period\": \"<number>\"\n    },\n    \"timeOfDays\": {\n      \"average\": \"<number>\",\n      \"timeOfDay\": \"<string>\"\n    },\n    \"daysOfWeek\": {\n      \"average\": \"<number>\",\n      \"dayOfWeek\": \"<string>\"\n    }\n  },\n  \"results\": {},\n  \"opponents\": [\n    {\n      \"opponent\": \"<string>\",\n      \"games\": \"<number>\",\n      \"win\": \"<number>\",\n      \"draw\": \"<number>\",\n      \"loss\": \"<number>\"\n    },\n    {\n      \"opponent\": \"<string>\",\n      \"games\": \"<number>\",\n      \"win\": \"<number>\",\n      \"draw\": \"<number>\",\n      \"loss\": \"<number>\"\n    }\n  ]\n}","cookie":[],"_postman_previewlanguage":"json"}],"event":[],"protocolProfileBehavior":{"disableBodyPruning":true}}]},{"name":"accuracy","description":"","item":[{"id":"a24c4ac4-9d8c-44ba-9775-a4e9141cf397","name":"Insights Controller get Accuracy Insights","request":{"name":"Insights Controller get Accuracy Insights","description":{},"url":{"path":["v1","chess","players",":username","insights","accuracy"],"host":["{{baseUrl}}"],"query":[],"variable":[{"type":"any","value":"<string>","key":"username","disabled":false,"description":{"content":"(Required) ","type":"text/plain"}}]},"header":[{"key":"Accept","value":"application/json"}],"method":"GET","body":{},"auth":null},"response":[{"id":"4b7d8f82-1cf4-43b8-be4b-0569e4658586","originalRequest":{"url":{"path":["v1","chess","players",":username","insights","accuracy"],"host":["{{baseUrl}}"],"query":[],"variable":[]},"header":[{"key":"Accept","value":"application/json"}],"method":"GET","body":{}},"status":"OK","code":200,"header":[{"key":"Content-Type","value":"application/json"}],"body":"{\n  \"username\": \"<string>\",\n  \"games\": {\n    \"total\": \"<number>\",\n    \"win\": \"<number>\",\n    \"draw\": \"<number>\",\n    \"loss\": \"<number>\",\n    \"periods\": [\n      \"<string>\",\n      \"<string>\"\n    ],\n    \"timeOfDays\": [\n      \"<string>\",\n      \"<string>\"\n    ],\n    \"daysOfWeek\": [\n      \"<string>\",\n      \"<string>\"\n    ]\n  },\n  \"accuracy\": {\n    \"average\": \"<number>\",\n    \"win\": \"<number>\",\n    \"draw\": \"<number>\",\n    \"loss\": \"<number>\",\n    \"periods\": {\n      \"average\": \"<number>\",\n      \"period\": \"<number>\"\n    },\n    \"timeOfDays\": {\n      \"average\": \"<number>\",\n      \"timeOfDay\": \"<string>\"\n    },\n    \"daysOfWeek\": {\n      \"average\": \"<number>\",\n      \"dayOfWeek\": \"<string>\"\n    }\n  },\n  \"results\": {},\n  \"opponents\": [\n    {\n      \"opponent\": \"<string>\",\n      \"games\": \"<number>\",\n      \"win\": \"<number>\",\n      \"draw\": \"<number>\",\n      \"loss\": \"<number>\"\n    },\n    {\n      \"opponent\": \"<string>\",\n      \"games\": \"<number>\",\n      \"win\": \"<number>\",\n      \"draw\": \"<number>\",\n      \"loss\": \"<number>\"\n    }\n  ]\n}","cookie":[],"_postman_previewlanguage":"json"}],"event":[],"protocolProfileBehavior":{"disableBodyPruning":true}}]},{"name":"results","description":"","item":[{"id":"26da8717-bbb0-4176-ba49-bc0a2e465207","name":"Insights Controller get Results Insights","request":{"name":"Insights Controller get Results Insights","description":{},"url":{"path":["v1","chess","players",":username","insights","results"],"host":["{{baseUrl}}"],"query":[],"variable":[{"type":"any","value":"<string>","key":"username","disabled":false,"description":{"content":"(Required) ","type":"text/plain"}}]},"header":[{"key":"Accept","value":"application/json"}],"method":"GET","body":{},"auth":null},"response":[{"id":"b433a672-2c66-4a13-b992-720189db9a4c","originalRequest":{"url":{"path":["v1","chess","players",":username","insights","results"],"host":["{{baseUrl}}"],"query":[],"variable":[]},"header":[{"key":"Accept","value":"application/json"}],"method":"GET","body":{}},"status":"OK","code":200,"header":[{"key":"Content-Type","value":"application/json"}],"body":"{\n  \"username\": \"<string>\",\n  \"games\": {\n    \"total\": \"<number>\",\n    \"win\": \"<number>\",\n    \"draw\": \"<number>\",\n    \"loss\": \"<number>\",\n    \"periods\": [\n      \"<string>\",\n      \"<string>\"\n    ],\n    \"timeOfDays\": [\n      \"<string>\",\n      \"<string>\"\n    ],\n    \"daysOfWeek\": [\n      \"<string>\",\n      \"<string>\"\n    ]\n  },\n  \"accuracy\": {\n    \"average\": \"<number>\",\n    \"win\": \"<number>\",\n    \"draw\": \"<number>\",\n    \"loss\": \"<number>\",\n    \"periods\": {\n      \"average\": \"<number>\",\n      \"period\": \"<number>\"\n    },\n    \"timeOfDays\": {\n      \"average\": \"<number>\",\n      \"timeOfDay\": \"<string>\"\n    },\n    \"daysOfWeek\": {\n      \"average\": \"<number>\",\n      \"dayOfWeek\": \"<string>\"\n    }\n  },\n  \"results\": {},\n  \"opponents\": [\n    {\n      \"opponent\": \"<string>\",\n      \"games\": \"<number>\",\n      \"win\": \"<number>\",\n      \"draw\": \"<number>\",\n      \"loss\": \"<number>\"\n    },\n    {\n      \"opponent\": \"<string>\",\n      \"games\": \"<number>\",\n      \"win\": \"<number>\",\n      \"draw\": \"<number>\",\n      \"loss\": \"<number>\"\n    }\n  ]\n}","cookie":[],"_postman_previewlanguage":"json"}],"event":[],"protocolProfileBehavior":{"disableBodyPruning":true}}]},{"name":"opponents","description":"","item":[{"id":"9efb1c27-38bd-43d0-af1e-112a58562cd9","name":"Insights Controller get Results Opponents","request":{"name":"Insights Controller get Results Opponents","description":{},"url":{"path":["v1","chess","players",":username","insights","opponents"],"host":["{{baseUrl}}"],"query":[],"variable":[{"type":"any","value":"<string>","key":"username","disabled":false,"description":{"content":"(Required) ","type":"text/plain"}}]},"header":[{"key":"Accept","value":"application/json"}],"method":"GET","body":{},"auth":null},"response":[{"id":"f1f3af8b-ac62-4694-af3a-6f76adbfa517","originalRequest":{"url":{"path":["v1","chess","players",":username","insights","opponents"],"host":["{{baseUrl}}"],"query":[],"variable":[]},"header":[{"key":"Accept","value":"application/json"}],"method":"GET","body":{}},"status":"OK","code":200,"header":[{"key":"Content-Type","value":"application/json"}],"body":"{\n  \"username\": \"<string>\",\n  \"games\": {\n    \"total\": \"<number>\",\n    \"win\": \"<number>\",\n    \"draw\": \"<number>\",\n    \"loss\": \"<number>\",\n    \"periods\": [\n      \"<string>\",\n      \"<string>\"\n    ],\n    \"timeOfDays\": [\n      \"<string>\",\n      \"<string>\"\n    ],\n    \"daysOfWeek\": [\n      \"<string>\",\n      \"<string>\"\n    ]\n  },\n  \"accuracy\": {\n    \"average\": \"<number>\",\n    \"win\": \"<number>\",\n    \"draw\": \"<number>\",\n    \"loss\": \"<number>\",\n    \"periods\": {\n      \"average\": \"<number>\",\n      \"period\": \"<number>\"\n    },\n    \"timeOfDays\": {\n      \"average\": \"<number>\",\n      \"timeOfDay\": \"<string>\"\n    },\n    \"daysOfWeek\": {\n      \"average\": \"<number>\",\n      \"dayOfWeek\": \"<string>\"\n    }\n  },\n  \"results\": {},\n  \"opponents\": [\n    {\n      \"opponent\": \"<string>\",\n      \"games\": \"<number>\",\n      \"win\": \"<number>\",\n      \"draw\": \"<number>\",\n      \"loss\": \"<number>\"\n    },\n    {\n      \"opponent\": \"<string>\",\n      \"games\": \"<number>\",\n      \"win\": \"<number>\",\n      \"draw\": \"<number>\",\n      \"loss\": \"<number>\"\n    }\n  ]\n}","cookie":[],"_postman_previewlanguage":"json"}],"event":[],"protocolProfileBehavior":{"disableBodyPruning":true}}]}]}]}]},{"name":"streamers","description":"","item":[{"id":"7b1de060-eb4d-4d09-abe2-41f85495b69e","name":"Streamers Controller get Streamers","request":{"name":"Streamers Controller get Streamers","description":{},"url":{"path":["v1","chess","streamers"],"host":["{{baseUrl}}"],"query":[{"disabled":false,"description":{"content":"title","type":"text/plain"},"key":"title","value":"<string>"},{"disabled":false,"description":{"content":"country","type":"text/plain"},"key":"country","value":"<string>"}],"variable":[]},"header":[{"key":"Accept","value":"application/json"}],"method":"GET","body":{},"auth":null},"response":[{"id":"7938f711-bdc9-4e58-98a1-e124d1f982b7","originalRequest":{"url":{"path":["v1","chess","streamers"],"host":["{{baseUrl}}"],"query":[{"disabled":false,"description":{"content":"title","type":"text/plain"},"key":"title","value":"<string>"},{"disabled":false,"description":{"content":"country","type":"text/plain"},"key":"country","value":"<string>"}],"variable":[]},"header":[{"key":"Accept","value":"application/json"}],"method":"GET","body":{}},"status":"OK","code":200,"header":[{"key":"Content-Type","value":"application/json"}],"body":"{\n  \"total\": \"<number>\",\n  \"players\": [],\n  \"countries\": []\n}","cookie":[],"_postman_previewlanguage":"json"}],"event":[],"protocolProfileBehavior":{"disableBodyPruning":true}}]},{"name":"titled","description":"","item":[{"id":"3ba20ab5-8915-4197-a832-93df0c8e0600","name":"Titled Controller get Titles","request":{"name":"Titled Controller get Titles","description":{},"url":{"path":["v1","chess","titled"],"host":["{{baseUrl}}"],"query":[],"variable":[]},"header":[{"key":"Accept","value":"application/json"}],"method":"GET","body":{},"auth":null},"response":[{"id":"fd4486e7-5416-4355-9bb5-274fedd8789a","originalRequest":{"url":{"path":["v1","chess","titled"],"host":["{{baseUrl}}"],"query":[],"variable":[]},"header":[{"key":"Accept","value":"application/json"}],"method":"GET","body":{}},"status":"OK","code":200,"header":[{"key":"Content-Type","value":"application/json"}],"body":"{\n  \"total\": \"<number>\",\n  \"titles\": [\n    \"<string>\",\n    \"<string>\"\n  ]\n}","cookie":[],"_postman_previewlanguage":"json"}],"event":[],"protocolProfileBehavior":{"disableBodyPruning":true}},{"name":"{title}","description":"","item":[{"id":"b03b74ef-2fb2-4c9e-9108-ba423e7012b8","name":"Titled Controller get Titled Stats","request":{"name":"Titled Controller get Titled Stats","description":{},"url":{"path":["v1","chess","titled",":title"],"host":["{{baseUrl}}"],"query":[{"disabled":false,"description":{"content":"cache","type":"text/plain"},"key":"cache","value":"<boolean>"},{"disabled":false,"description":{"content":"timeRange","type":"text/plain"},"key":"timeRange","value":"<string>"}],"variable":[{"type":"any","value":"<string>","key":"title","disabled":false,"description":{"content":"(Required) title","type":"text/plain"}}]},"header":[{"key":"Accept","value":"application/json"}],"method":"GET","body":{},"auth":null},"response":[{"id":"53678780-1dfd-47c1-b064-d670e4825641","originalRequest":{"url":{"path":["v1","chess","titled",":title"],"host":["{{baseUrl}}"],"query":[{"disabled":false,"description":{"content":"cache","type":"text/plain"},"key":"cache","value":"<boolean>"},{"disabled":false,"description":{"content":"timeRange","type":"text/plain"},"key":"timeRange","value":"<string>"}],"variable":[]},"header":[{"key":"Accept","value":"application/json"}],"method":"GET","body":{}},"status":"OK","code":200,"header":[{"key":"Content-Type","value":"application/json"}],"body":"{\n  \"averageRapidRating\": \"<number>\",\n  \"maxRapidRating\": \"<number>\",\n  \"averageBlitzRating\": \"<number>\",\n  \"maxBlitzRating\": \"<number>\",\n  \"averageBulletRating\": \"<number>\",\n  \"maxBulletRating\": \"<number>\",\n  \"total\": \"<number>\",\n  \"players\": []\n}","cookie":[],"_postman_previewlanguage":"json"}],"event":[],"protocolProfileBehavior":{"disableBodyPruning":true}}]}]},{"name":"countries","description":"","item":[{"id":"584cb898-ef07-4b0a-bf4d-4ed26ac21e5c","name":"Countries Controller get Countries","request":{"name":"Countries Controller get Countries","description":{},"url":{"path":["v1","chess","countries"],"host":["{{baseUrl}}"],"query":[{"disabled":false,"description":{"content":"(Required) ","type":"text/plain"},"key":"cache","value":"<boolean>"}],"variable":[]},"header":[{"key":"Accept","value":"application/json"}],"method":"GET","body":{},"auth":null},"response":[{"id":"803c08c4-99a0-4782-b1da-48583b47273b","originalRequest":{"url":{"path":["v1","chess","countries"],"host":["{{baseUrl}}"],"query":[{"disabled":false,"description":{"content":"(Required) ","type":"text/plain"},"key":"cache","value":"<boolean>"}],"variable":[]},"header":[{"key":"Accept","value":"application/json"}],"method":"GET","body":{}},"status":"OK","code":200,"header":[{"key":"Content-Type","value":"application/json"}],"body":"{}","cookie":[],"_postman_previewlanguage":"json"}],"event":[],"protocolProfileBehavior":{"disableBodyPruning":true}},{"name":"{code}","description":"","item":[{"id":"96061e18-f894-4a53-92a4-62273e5bbbd5","name":"Countries Controller get Titled Players By Country","request":{"name":"Countries Controller get Titled Players By Country","description":{},"url":{"path":["v1","chess","countries",":code"],"host":["{{baseUrl}}"],"query":[{"disabled":false,"description":{"content":"(Required) ","type":"text/plain"},"key":"cache","value":"<boolean>"}],"variable":[{"type":"any","value":"<string>","key":"code","disabled":false,"description":{"content":"(Required) ","type":"text/plain"}}]},"header":[{"key":"Accept","value":"application/json"}],"method":"GET","body":{},"auth":null},"response":[{"id":"c4997526-b7c4-445a-98cb-821ce381604c","originalRequest":{"url":{"path":["v1","chess","countries",":code"],"host":["{{baseUrl}}"],"query":[{"disabled":false,"description":{"content":"(Required) ","type":"text/plain"},"key":"cache","value":"<boolean>"}],"variable":[]},"header":[{"key":"Accept","value":"application/json"}],"method":"GET","body":{}},"status":"OK","code":200,"header":[{"key":"Content-Type","value":"application/json"}],"body":"{\n  \"total\": 0,\n  \"regions\": [],\n  \"subregions\": [],\n  \"countries\": []\n}","cookie":[],"_postman_previewlanguage":"json"}],"event":[],"protocolProfileBehavior":{"disableBodyPruning":true}}]}]}]},{"name":"countries","description":"","item":[{"id":"96c632a7-f0d5-46c5-ade7-c864a0660a57","name":"Countries Controller get Countries","request":{"name":"Countries Controller get Countries","description":{},"url":{"path":["v1","countries"],"host":["{{baseUrl}}"],"query":[{"disabled":false,"description":{"content":"Timezone","type":"text/plain"},"key":"timezone","value":"<string>"},{"disabled":false,"description":{"content":"Language","type":"text/plain"},"key":"language","value":"<string>"},{"disabled":false,"description":{"content":"Currency","type":"text/plain"},"key":"currency","value":"<string>"},{"disabled":false,"description":{"content":"Subregion","type":"text/plain"},"key":"subregion","value":"<string>"},{"disabled":false,"description":{"content":"Region","type":"text/plain"},"key":"region","value":"AFRICA"},{"disabled":false,"description":{"content":"United Nation Member","type":"text/plain"},"key":"unMember","value":"<boolean>"},{"disabled":false,"description":{"content":"Capital","type":"text/plain"},"key":"capital","value":"<string>"},{"disabled":false,"description":{"content":"Name","type":"text/plain"},"key":"name","value":"<string>"}],"variable":[]},"header":[{"key":"Accept","value":"application/json"}],"method":"GET","body":{},"auth":null},"response":[{"id":"8d1cf04e-afb2-4807-8532-536a47a41881","name":"List of Countries","originalRequest":{"url":{"path":["v1","countries"],"host":["{{baseUrl}}"],"query":[{"disabled":false,"description":{"content":"Timezone","type":"text/plain"},"key":"timezone","value":"<string>"},{"disabled":false,"description":{"content":"Language","type":"text/plain"},"key":"language","value":"<string>"},{"disabled":false,"description":{"content":"Currency","type":"text/plain"},"key":"currency","value":"<string>"},{"disabled":false,"description":{"content":"Subregion","type":"text/plain"},"key":"subregion","value":"<string>"},{"disabled":false,"description":{"content":"Region","type":"text/plain"},"key":"region","value":"AFRICA"},{"disabled":false,"description":{"content":"United Nation Member","type":"text/plain"},"key":"unMember","value":"<boolean>"},{"disabled":false,"description":{"content":"Capital","type":"text/plain"},"key":"capital","value":"<string>"},{"disabled":false,"description":{"content":"Name","type":"text/plain"},"key":"name","value":"<string>"}],"variable":[]},"header":[{"key":"Accept","value":"application/json"}],"method":"GET","body":{}},"status":"OK","code":200,"header":[{"key":"Content-Type","value":"application/json"}],"body":"{\n  \"total\": 0,\n  \"regions\": [],\n  \"subregions\": [],\n  \"countries\": []\n}","cookie":[],"_postman_previewlanguage":"json"}],"event":[],"protocolProfileBehavior":{"disableBodyPruning":true}},{"name":"{code}","description":"","item":[{"id":"cf534d43-9a0d-44d9-9f2a-a45c0bfb9247","name":"Countries Controller get Country","request":{"name":"Countries Controller get Country","description":{},"url":{"path":["v1","countries",":code"],"host":["{{baseUrl}}"],"query":[],"variable":[{"type":"any","value":"<string>","key":"code","disabled":false,"description":{"content":"(Required) ","type":"text/plain"}}]},"header":[{"key":"Accept","value":"application/json"}],"method":"GET","body":{},"auth":null},"response":[{"id":"1060c433-9e99-4a28-8153-77de8acba4aa","name":"Get Country by Code","originalRequest":{"url":{"path":["v1","countries",":code"],"host":["{{baseUrl}}"],"query":[],"variable":[]},"header":[{"key":"Accept","value":"application/json"}],"method":"GET","body":{}},"status":"OK","code":200,"header":[{"key":"Content-Type","value":"application/json"}],"body":"{}","cookie":[],"_postman_previewlanguage":"json"}],"event":[],"protocolProfileBehavior":{"disableBodyPruning":true}}]},{"name":"currencies","description":"","item":[{"id":"4916bb43-9e8b-4464-93bf-12fb5b9b33ec","name":"Countries Controller get Currencies","request":{"name":"Countries Controller get Currencies","description":{},"url":{"path":["v1","countries","currencies"],"host":["{{baseUrl}}"],"query":[],"variable":[]},"header":[{"key":"Accept","value":"application/json"}],"method":"GET","body":{},"auth":null},"response":[{"id":"b7da318e-267c-48b1-9595-4b79f0a5e53d","name":"List of Currencies","originalRequest":{"url":{"path":["v1","countries","currencies"],"host":["{{baseUrl}}"],"query":[],"variable":[]},"header":[{"key":"Accept","value":"application/json"}],"method":"GET","body":{}},"status":"OK","code":200,"header":[{"key":"Content-Type","value":"application/json"}],"body":"{\n  \"total\": 0,\n  \"currencies\": []\n}","cookie":[],"_postman_previewlanguage":"json"}],"event":[],"protocolProfileBehavior":{"disableBodyPruning":true}}]}]},{"name":"currencies","description":"","item":[{"id":"5c3d1b2d-1d21-4ce9-9d6f-dfb5bbd21276","name":"Currencies Controller get Currencies","request":{"name":"Currencies Controller get Currencies","description":{},"url":{"path":["v1","currencies"],"host":["{{baseUrl}}"],"query":[],"variable":[]},"header":[{"key":"Accept","value":"application/json"}],"method":"GET","body":{},"auth":null},"response":[{"id":"a307bce1-9cfb-45cd-be6c-5556cbf9ae7a","name":"List of Currencies","originalRequest":{"url":{"path":["v1","currencies"],"host":["{{baseUrl}}"],"query":[],"variable":[]},"header":[{"key":"Accept","value":"application/json"}],"method":"GET","body":{}},"status":"OK","code":200,"header":[{"key":"Content-Type","value":"application/json"}],"body":"{\n  \"total\": 0,\n  \"currencies\": []\n}","cookie":[],"_postman_previewlanguage":"json"}],"event":[],"protocolProfileBehavior":{"disableBodyPruning":true}}]},{"name":"languages","description":"","item":[{"id":"e8cfefea-50d6-4de5-8ab4-d7aed67eafed","name":"Languages Controller get Languages","request":{"name":"Languages Controller get Languages","description":{},"url":{"path":["v1","languages"],"host":["{{baseUrl}}"],"query":[],"variable":[]},"header":[{"key":"Accept","value":"application/json"}],"method":"GET","body":{},"auth":null},"response":[{"id":"2a195b89-75e2-44b7-81b6-0bc033b7fb88","name":"List of Languages","originalRequest":{"url":{"path":["v1","languages"],"host":["{{baseUrl}}"],"query":[],"variable":[]},"header":[{"key":"Accept","value":"application/json"}],"method":"GET","body":{}},"status":"OK","code":200,"header":[{"key":"Content-Type","value":"application/json"}],"body":"{\n  \"total\": 0,\n  \"languages\": []\n}","cookie":[],"_postman_previewlanguage":"json"}],"event":[],"protocolProfileBehavior":{"disableBodyPruning":true}}]},{"name":"organizations","description":"","item":[{"id":"03e267c3-8be2-48d1-8ca4-7284cadb3b5f","name":"Organizations Controller get Organizations","request":{"name":"Organizations Controller get Organizations","description":{},"url":{"path":["v1","organizations"],"host":["{{baseUrl}}"],"query":[],"variable":[]},"header":[{"key":"Accept","value":"application/json"}],"method":"GET","body":{},"auth":null},"response":[{"id":"8dfb6e7c-d4f1-41e7-9f27-198e0d55ec74","name":"List of Organizations","originalRequest":{"url":{"path":["v1","organizations"],"host":["{{baseUrl}}"],"query":[],"variable":[]},"header":[{"key":"Accept","value":"application/json"}],"method":"GET","body":{}},"status":"OK","code":200,"header":[{"key":"Content-Type","value":"application/json"}],"body":"{\n  \"total\": 0,\n  \"organizations\": []\n}","cookie":[],"_postman_previewlanguage":"json"}],"event":[],"protocolProfileBehavior":{"disableBodyPruning":true}},{"name":"{code}","description":"","item":[{"id":"9a6fa3e0-cc10-4944-be66-c7b2c8fad754","name":"Organizations Controller get Organization","request":{"name":"Organizations Controller get Organization","description":{},"url":{"path":["v1","organizations",":code"],"host":["{{baseUrl}}"],"query":[],"variable":[{"type":"any","value":"<string>","key":"code","disabled":false,"description":{"content":"(Required) Organization Code","type":"text/plain"}}]},"header":[{"key":"Accept","value":"application/json"}],"method":"GET","body":{},"auth":null},"response":[{"id":"ee51e792-4574-412b-9106-6e8ec44af979","name":"Get Organization by Code","originalRequest":{"url":{"path":["v1","organizations",":code"],"host":["{{baseUrl}}"],"query":[],"variable":[]},"header":[{"key":"Accept","value":"application/json"}],"method":"GET","body":{}},"status":"OK","code":200,"header":[{"key":"Content-Type","value":"application/json"}],"body":"{}","cookie":[],"_postman_previewlanguage":"json"}],"event":[],"protocolProfileBehavior":{"disableBodyPruning":true}}]}]},{"name":"vietnam","description":"","item":[{"name":"ethnic-groups","description":"","item":[{"id":"4890526a-7891-465f-a4f3-6532dfcd3a67","name":"Vietnam Controller get Ethnic Groups","request":{"name":"Vietnam Controller get Ethnic Groups","description":{},"url":{"path":["v1","vietnam","ethnic-groups"],"host":["{{baseUrl}}"],"query":[],"variable":[]},"header":[{"key":"Accept","value":"application/json"}],"method":"GET","body":{},"auth":null},"response":[{"id":"2c7ff1be-b231-4d3b-8375-5024e68aee8d","name":"List of Ethnic Groups","originalRequest":{"url":{"path":["v1","vietnam","ethnic-groups"],"host":["{{baseUrl}}"],"query":[],"variable":[]},"header":[{"key":"Accept","value":"application/json"}],"method":"GET","body":{}},"status":"OK","code":200,"header":[{"key":"Content-Type","value":"application/json"}],"body":"{\n  \"total\": 0,\n  \"ethnicGroups\": []\n}","cookie":[],"_postman_previewlanguage":"json"}],"event":[],"protocolProfileBehavior":{"disableBodyPruning":true}}]},{"name":"license-plates","description":"","item":[{"id":"f65645c9-f225-4b18-9417-27d5dc176e85","name":"Vietnam Controller get License Plates","request":{"name":"Vietnam Controller get License Plates","description":{},"url":{"path":["v1","vietnam","license-plates"],"host":["{{baseUrl}}"],"query":[],"variable":[]},"header":[{"key":"Accept","value":"application/json"}],"method":"GET","body":{},"auth":null},"response":[{"id":"a1c201a7-572a-41e7-9927-03026edcdee6","name":"List of License Plates","originalRequest":{"url":{"path":["v1","vietnam","license-plates"],"host":["{{baseUrl}}"],"query":[],"variable":[]},"header":[{"key":"Accept","value":"application/json"}],"method":"GET","body":{}},"status":"OK","code":200,"header":[{"key":"Content-Type","value":"application/json"}],"body":"{\n  \"total\": 0,\n  \"licensePlates\": []\n}","cookie":[],"_postman_previewlanguage":"json"}],"event":[],"protocolProfileBehavior":{"disableBodyPruning":true}},{"name":"{code}","description":"","item":[{"id":"31fa3d06-d3d1-4d04-923e-314229a031f2","name":"Vietnam Controller get License Plate","request":{"name":"Vietnam Controller get License Plate","description":{},"url":{"path":["v1","vietnam","license-plates",":code"],"host":["{{baseUrl}}"],"query":[],"variable":[{"type":"any","value":"<string>","key":"code","disabled":false,"description":{"content":"(Required) ","type":"text/plain"}}]},"header":[{"key":"Accept","value":"application/json"}],"method":"GET","body":{},"auth":null},"response":[{"id":"e4a5f23b-7da7-4767-b58e-9b56d8d7606e","name":"Get License Plate by Code","originalRequest":{"url":{"path":["v1","vietnam","license-plates",":code"],"host":["{{baseUrl}}"],"query":[],"variable":[]},"header":[{"key":"Accept","value":"application/json"}],"method":"GET","body":{}},"status":"OK","code":200,"header":[{"key":"Content-Type","value":"application/json"}],"body":"{}","cookie":[],"_postman_previewlanguage":"json"}],"event":[],"protocolProfileBehavior":{"disableBodyPruning":true}}]}]}]},{"name":"crypto","description":"","item":[{"name":"coins","description":"","item":[{"id":"744d7f39-b34b-422d-bd70-11f0e788c20e","name":"Crypto Controller get Countries","request":{"name":"Crypto Controller get Countries","description":{},"url":{"path":["v1","crypto","coins"],"host":["{{baseUrl}}"],"query":[{"disabled":false,"description":{"content":"(Required) ","type":"text/plain"},"key":"limit","value":"<number>"}],"variable":[]},"header":[{"key":"Accept","value":"application/json"}],"method":"GET","body":{},"auth":null},"response":[{"id":"315f3c3f-0b42-45ae-bac9-0f5b27122906","name":"List of Crypto Coins","originalRequest":{"url":{"path":["v1","crypto","coins"],"host":["{{baseUrl}}"],"query":[{"disabled":false,"description":{"content":"(Required) ","type":"text/plain"},"key":"limit","value":"<number>"}],"variable":[]},"header":[{"key":"Accept","value":"application/json"}],"method":"GET","body":{}},"status":"OK","code":200,"header":[{"key":"Content-Type","value":"application/json"}],"body":"{\n  \"total\": 0,\n  \"coins\": []\n}","cookie":[],"_postman_previewlanguage":"json"}],"event":[],"protocolProfileBehavior":{"disableBodyPruning":true}}]}]},{"name":"forex","description":"","item":[{"name":"rates","description":"","item":[{"id":"e37d009b-5990-4cfa-bfee-3ff285eaddd7","name":"Forex Controller get Rates","request":{"name":"Forex Controller get Rates","description":{},"url":{"path":["v1","forex","rates"],"host":["{{baseUrl}}"],"query":[{"disabled":false,"description":{"content":"Base","type":"text/plain"},"key":"base","value":"<string>"},{"disabled":false,"description":{"content":"Amount","type":"text/plain"},"key":"amount","value":"<number>"}],"variable":[]},"header":[{"key":"Accept","value":"application/json"}],"method":"GET","body":{},"auth":null},"response":[{"id":"794765e3-1a83-4494-a6d2-0b1bc3605298","name":"List of Forex Rates","originalRequest":{"url":{"path":["v1","forex","rates"],"host":["{{baseUrl}}"],"query":[{"disabled":false,"description":{"content":"Base","type":"text/plain"},"key":"base","value":"<string>"},{"disabled":false,"description":{"content":"Amount","type":"text/plain"},"key":"amount","value":"<number>"}],"variable":[]},"header":[{"key":"Accept","value":"application/json"}],"method":"GET","body":{}},"status":"OK","code":200,"header":[{"key":"Content-Type","value":"application/json"}],"body":"{\n  \"total\": \"<number>\",\n  \"amount\": \"<number>\",\n  \"base\": \"<string>\",\n  \"rates\": [\n    {\n      \"rate\": \"<number>\",\n      \"code\": \"<string>\",\n      \"name\": \"<string>\"\n    },\n    {\n      \"rate\": \"<number>\",\n      \"code\": \"<string>\",\n      \"name\": \"<string>\"\n    }\n  ]\n}","cookie":[],"_postman_previewlanguage":"json"}],"event":[],"protocolProfileBehavior":{"disableBodyPruning":true}}]}]},{"name":"github","description":"","item":[{"name":"languages","description":"","item":[{"id":"4c96cd9b-9dfd-4ee2-9f16-0c22569d88d6","name":"Git Hub Controller get Languages","request":{"name":"Git Hub Controller get Languages","description":{},"url":{"path":["v1","github","languages"],"host":["{{baseUrl}}"],"query":[],"variable":[]},"header":[{"key":"Accept","value":"application/json"}],"method":"GET","body":{},"auth":null},"response":[{"id":"00775d61-ed29-48d1-b638-a25802ffc392","name":"List of Languages","originalRequest":{"url":{"path":["v1","github","languages"],"host":["{{baseUrl}}"],"query":[],"variable":[]},"header":[{"key":"Accept","value":"application/json"}],"method":"GET","body":{}},"status":"OK","code":200,"header":[{"key":"Content-Type","value":"application/json"}],"body":"{\n  \"total\": \"<number>\",\n  \"languages\": []\n}","cookie":[],"_postman_previewlanguage":"json"}],"event":[],"protocolProfileBehavior":{"disableBodyPruning":true}}]}]},{"name":"health","description":"","item":[{"id":"063a599b-b686-4583-ab43-acf46961d55f","name":"Health Controller get Health","request":{"name":"Health Controller get Health","description":{},"url":{"path":["v1","health"],"host":["{{baseUrl}}"],"query":[],"variable":[]},"header":[{"key":"Accept","value":"application/json"}],"method":"GET","body":{},"auth":null},"response":[{"id":"523a022b-9d50-4d11-99ba-013f08e0e8bb","name":"State of the Server","originalRequest":{"url":{"path":["v1","health"],"host":["{{baseUrl}}"],"query":[],"variable":[]},"header":[{"key":"Accept","value":"application/json"}],"method":"GET","body":{}},"status":"OK","code":200,"header":[{"key":"Content-Type","value":"application/json"}],"body":"{\n  \"status\": \"\"\n}","cookie":[],"_postman_previewlanguage":"json"}],"event":[],"protocolProfileBehavior":{"disableBodyPruning":true}}]},{"name":"news","description":"","item":[{"name":"google","description":"","item":[{"id":"272f6d42-b41a-43fe-91aa-433900182fa0","name":"News Controller get Google","request":{"name":"News Controller get Google","description":{},"url":{"path":["v1","news","google"],"host":["{{baseUrl}}"],"query":[],"variable":[]},"header":[{"key":"Accept","value":"application/json"}],"method":"GET","body":{},"auth":null},"response":[{"id":"404a3b0c-68ee-477c-885e-06e4f9bd46c7","name":"List of Google Trends","originalRequest":{"url":{"path":["v1","news","google"],"host":["{{baseUrl}}"],"query":[],"variable":[]},"header":[{"key":"Accept","value":"application/json"}],"method":"GET","body":{}},"status":"OK","code":200,"header":[{"key":"Content-Type","value":"application/json"}],"body":"{\n  \"total\": 0,\n  \"countries\": []\n}","cookie":[],"_postman_previewlanguage":"json"}],"event":[],"protocolProfileBehavior":{"disableBodyPruning":true}}]},{"name":"sources","description":"","item":[{"id":"383bbe5c-f574-4fe4-b9bf-3ff39919df9b","name":"News Controller get Sources","request":{"name":"News Controller get Sources","description":{},"url":{"path":["v1","news","sources"],"host":["{{baseUrl}}"],"query":[],"variable":[]},"header":[{"key":"Accept","value":"application/json"}],"method":"GET","body":{},"auth":null},"response":[{"id":"4c45c4e6-6630-4270-b70e-246e998e95ad","name":"List of News Sources","originalRequest":{"url":{"path":["v1","news","sources"],"host":["{{baseUrl}}"],"query":[],"variable":[]},"header":[{"key":"Accept","value":"application/json"}],"method":"GET","body":{}},"status":"OK","code":200,"header":[{"key":"Content-Type","value":"application/json"}],"body":"{\n  \"total\": 0,\n  \"sources\": []\n}","cookie":[],"_postman_previewlanguage":"json"}],"event":[],"protocolProfileBehavior":{"disableBodyPruning":true}}]}]},{"name":"tarot","description":"","item":[{"name":"cards","description":"","item":[{"id":"4521e46e-8521-4ce3-b6cb-8155149b9fe4","name":"Tarot Controller get Cards","request":{"name":"Tarot Controller get Cards","description":{},"url":{"path":["v1","tarot","cards"],"host":["{{baseUrl}}"],"query":[{"disabled":false,"description":{"content":"Tarot Type","type":"text/plain"},"key":"type","value":"MINOR"},{"disabled":false,"description":{"content":"Tarot Suit","type":"text/plain"},"key":"suit","value":"<string>"},{"disabled":false,"description":{"content":"Limit","type":"text/plain"},"key":"limit","value":"<number>"}],"variable":[]},"header":[{"key":"Accept","value":"application/json"}],"method":"GET","body":{},"auth":null},"response":[{"id":"fbd8c985-eef9-4346-8b61-7126527d8e04","name":"List of Tarot Cards","originalRequest":{"url":{"path":["v1","tarot","cards"],"host":["{{baseUrl}}"],"query":[{"disabled":false,"description":{"content":"Tarot Type","type":"text/plain"},"key":"type","value":"MINOR"},{"disabled":false,"description":{"content":"Tarot Suit","type":"text/plain"},"key":"suit","value":"<string>"},{"disabled":false,"description":{"content":"Limit","type":"text/plain"},"key":"limit","value":"<number>"}],"variable":[]},"header":[{"key":"Accept","value":"application/json"}],"method":"GET","body":{}},"status":"OK","code":200,"header":[{"key":"Content-Type","value":"application/json"}],"body":"{\n  \"total\": 0,\n  \"types\": \"MINOR\",\n  \"suits\": [\n    \"<string>\",\n    \"<string>\"\n  ],\n  \"cards\": []\n}","cookie":[],"_postman_previewlanguage":"json"}],"event":[],"protocolProfileBehavior":{"disableBodyPruning":true}},{"name":"{id}","description":"","item":[{"id":"39b0c056-6914-4818-9b3e-2a800297af48","name":"Tarot Controller get Card","request":{"name":"Tarot Controller get Card","description":{},"url":{"path":["v1","tarot","cards",":id"],"host":["{{baseUrl}}"],"query":[{"disabled":false,"description":{"content":"(Required) ","type":"text/plain"},"key":"id","value":"<string>"}],"variable":[{"type":"any","key":"id"}]},"header":[{"key":"Accept","value":"application/json"}],"method":"GET","body":{},"auth":null},"response":[{"id":"a1c7f737-1b52-4f6b-b832-0215f9d6cf3d","name":"Get Tarot Card by ID","originalRequest":{"url":{"path":["v1","tarot","cards",":id"],"host":["{{baseUrl}}"],"query":[{"disabled":false,"description":{"content":"(Required) ","type":"text/plain"},"key":"id","value":"<string>"}],"variable":[]},"header":[{"key":"Accept","value":"application/json"}],"method":"GET","body":{}},"status":"OK","code":200,"header":[{"key":"Content-Type","value":"application/json"}],"body":"{}","cookie":[],"_postman_previewlanguage":"json"}],"event":[],"protocolProfileBehavior":{"disableBodyPruning":true}}]}]}]},{"name":"words","description":"","item":[{"id":"b432a27b-b6e4-48d4-9b63-4cdfd92cfed9","name":"Words Controller get Words","request":{"name":"Words Controller get Words","description":{},"url":{"path":["v1","words"],"host":["{{baseUrl}}"],"query":[{"disabled":false,"description":{"content":"Offset","type":"text/plain"},"key":"offset","value":"<number>"},{"disabled":false,"description":{"content":"Limit","type":"text/plain"},"key":"limit","value":"<number>"}],"variable":[]},"header":[{"key":"Accept","value":"application/json"}],"method":"GET","body":{},"auth":null},"response":[{"id":"dc0bb86a-c7a9-4f38-bd60-0623911998aa","name":"List of Words","originalRequest":{"url":{"path":["v1","words"],"host":["{{baseUrl}}"],"query":[{"disabled":false,"description":{"content":"Offset","type":"text/plain"},"key":"offset","value":"<number>"},{"disabled":false,"description":{"content":"Limit","type":"text/plain"},"key":"limit","value":"<number>"}],"variable":[]},"header":[{"key":"Accept","value":"application/json"}],"method":"GET","body":{}},"status":"OK","code":200,"header":[{"key":"Content-Type","value":"application/json"}],"body":"{\n  \"limit\": 0,\n  \"offset\": 0,\n  \"total\": 0,\n  \"words\": []\n}","cookie":[],"_postman_previewlanguage":"json"}],"event":[],"protocolProfileBehavior":{"disableBodyPruning":true}},{"name":"{word}","description":"","item":[{"id":"c9b70dec-1e8d-41c5-903e-238d892ed79c","name":"Words Controller get Word","request":{"name":"Words Controller get Word","description":{},"url":{"path":["v1","words",":word"],"host":["{{baseUrl}}"],"query":[{"disabled":false,"description":{"content":"(Required) ","type":"text/plain"},"key":"word","value":"<string>"}],"variable":[{"type":"any","key":"word"}]},"header":[{"key":"Accept","value":"application/json"}],"method":"GET","body":{},"auth":null},"response":[{"id":"e6c6fd49-c5d3-4884-9b40-d496275bec4f","name":"Get Words Card by ID","originalRequest":{"url":{"path":["v1","words",":word"],"host":["{{baseUrl}}"],"query":[{"disabled":false,"description":{"content":"(Required) ","type":"text/plain"},"key":"word","value":"<string>"}],"variable":[]},"header":[{"key":"Accept","value":"application/json"}],"method":"GET","body":{}},"status":"OK","code":200,"header":[{"key":"Content-Type","value":"application/json"}],"body":"{}","cookie":[],"_postman_previewlanguage":"json"}],"event":[],"protocolProfileBehavior":{"disableBodyPruning":true}}]}]}]}],"event":[],"variable":[{"key":"baseUrl","value":"/"}],"info":{"_postman_id":"5caba65b-fbfa-4bc2-869d-77423966e58c","name":"hieudoanm","schema":"https://schema.getpostman.com/json/collection/v2.1.0/collection.json","description":{"content":"Hieu Doan","type":"text/plain"}}}