{
  "avatar": "https://images.chesscomfiles.com/uploads/v1/user/127704260.9faf19a8.200x200o.dc1fd85b9772.jpeg",
  "player_id": 127704260,
  "@id": "https://api.chess.com/pub/player/rafaeltumas",
  "url": "https://www.chess.com/member/Rafaeltumas",
  "name": "Rafael Tuma Soares",
  "username": "rafaeltumas",
  "title": "NM",
  "followers": 69,
  "country": "https://api.chess.com/pub/country/BR",
  "location": "Campo Mour\u00e3o",
  "last_online": 1776511284,
  "joined": 1615587299,
  "status": "premium",
  "is_streamer": false,
  "verified": false,
  "league": "Legend",
  "streaming_platforms": [],
  "chess_rapid": {
    "last": {
      "rating": 2046,
      "date": 1775229411,
      "rd": 49
    },
    "best": {
      "rating": 2054,
      "date": 1771526757,
      "game": "https://www.chess.com/game/live/164925229568"
    },
    "record": {
      "win": 170,
      "loss": 67,
      "draw": 7
    }
  },
  "chess_bullet": {
    "last": {
      "rating": 2105,
      "date": 1771435072,
      "rd": 55
    },
    "best": {
      "rating": 2105,
      "date": 1771435072,
      "game": "https://www.chess.com/game/live/164875026232"
    },
    "record": {
      "win": 500,
      "loss": 338,
      "draw": 22
    }
  },
  "chess_blitz": {
    "last": {
      "rating": 2041,
      "date": 1776259761,
      "rd": 58
    },
    "best": {
      "rating": 2141,
      "date": 1773589116,
      "game": "https://www.chess.com/game/live/102123868211"
    },
    "record": {
      "win": 623,
      "loss": 323,
      "draw": 43
    }
  },
  "fide": 2009,
  "tactics": {
    "highest": {
      "rating": 2341,
      "date": 1759456623
    },
    "lowest": {
      "rating": 2165,
      "date": 1775228742
    }
  },
  "puzzle_rush": {
    "best": {
      "total_attempts": 41,
      "score": 38
    }
  }
}