{
  "avatar": "https://images.chesscomfiles.com/uploads/v1/user/16514072.573e901a.200x200o.877926d2fc87.jpg",
  "player_id": 16514072,
  "@id": "https://api.chess.com/pub/player/dagurr",
  "url": "https://www.chess.com/member/DagurR",
  "name": "Dagur Ragnarsson",
  "username": "dagurr",
  "title": "IM",
  "followers": 91,
  "country": "https://api.chess.com/pub/country/IS",
  "last_online": 1775820244,
  "joined": 1395177314,
  "status": "premium",
  "is_streamer": false,
  "verified": false,
  "league": "Legend",
  "streaming_platforms": [],
  "chess_daily": {
    "last": {
      "rating": 799,
      "date": 1745246832,
      "rd": 258
    },
    "best": {
      "rating": 1200,
      "date": 1395177314,
      "game": "https://www.chess.com/game/daily/506512247"
    },
    "record": {
      "win": 3,
      "loss": 0,
      "draw": 0,
      "time_per_move": 95022,
      "timeout_percent": 0
    }
  },
  "chess960_daily": {
    "last": {
      "rating": 691,
      "date": 1610388992,
      "rd": 349
    },
    "record": {
      "win": 0,
      "loss": 0,
      "draw": 1,
      "time_per_move": 95022,
      "timeout_percent": 0
    }
  },
  "chess_rapid": {
    "last": {
      "rating": 2700,
      "date": 1701882657,
      "rd": 349
    },
    "best": {
      "rating": 2700,
      "date": 1701882657,
      "game": "https://www.chess.com/game/live/95621351009"
    },
    "record": {
      "win": 1,
      "loss": 0,
      "draw": 0
    }
  },
  "chess_bullet": {
    "last": {
      "rating": 2595,
      "date": 1700610185,
      "rd": 56
    },
    "best": {
      "rating": 2718,
      "date": 1629488426,
      "game": "https://www.chess.com/game/live/75753814485"
    },
    "record": {
      "win": 2861,
      "loss": 2130,
      "draw": 339
    }
  },
  "chess_blitz": {
    "last": {
      "rating": 2736,
      "date": 1772478551,
      "rd": 40
    },
    "best": {
      "rating": 2811,
      "date": 1767640825,
      "game": "https://www.chess.com/game/live/165383520126"
    },
    "record": {
      "win": 11219,
      "loss": 8587,
      "draw": 1665
    }
  },
  "fide": 2350,
  "tactics": {
    "highest": {
      "rating": 2571,
      "date": 1763382183
    },
    "lowest": {
      "rating": 2297,
      "date": 1763581933
    }
  },
  "puzzle_rush": {
    "best": {
      "total_attempts": 57,
      "score": 54
    }
  }
}