{
  "player_id": 16934378,
  "@id": "https://api.chess.com/pub/player/aspaclaria",
  "url": "https://www.chess.com/member/aspaclaria",
  "name": "Sergio Markeluk",
  "username": "aspaclaria",
  "title": "FM",
  "followers": 13,
  "country": "https://api.chess.com/pub/country/AR",
  "location": "Argentina",
  "last_online": 1776132510,
  "joined": 1397694680,
  "status": "premium",
  "is_streamer": false,
  "verified": false,
  "league": "Elite",
  "streaming_platforms": [],
  "chess_bullet": {
    "last": {
      "rating": 1770,
      "date": 1769787947,
      "rd": 20
    },
    "best": {
      "rating": 2088,
      "date": 1673813110,
      "game": "https://www.chess.com/game/live/79381386245"
    },
    "record": {
      "win": 11794,
      "loss": 13838,
      "draw": 526
    }
  },
  "chess_blitz": {
    "last": {
      "rating": 2107,
      "date": 1776132223,
      "rd": 39
    },
    "best": {
      "rating": 2121,
      "date": 1658160852,
      "game": "https://www.chess.com/game/live/50431139979"
    },
    "record": {
      "win": 1087,
      "loss": 1212,
      "draw": 141
    }
  },
  "tactics": {
    "highest": {
      "rating": 2442,
      "date": 1397694680
    },
    "lowest": {
      "rating": 2442,
      "date": 1397694680
    }
  },
  "puzzle_rush": {}
}