{
  "avatar": "https://images.chesscomfiles.com/uploads/v1/user/18206892.d4130b22.200x200o.50da65940490.jpeg",
  "player_id": 18206892,
  "@id": "https://api.chess.com/pub/player/anthonywirig",
  "url": "https://www.chess.com/member/AnthonyWirig",
  "name": "Anthony Wirig",
  "username": "anthonywirig",
  "title": "GM",
  "followers": 1454,
  "country": "https://api.chess.com/pub/country/FR",
  "last_online": 1776592468,
  "joined": 1406214208,
  "status": "premium",
  "is_streamer": false,
  "verified": false,
  "league": "Legend",
  "streaming_platforms": [],
  "chess_daily": {
    "last": {
      "rating": 1958,
      "date": 1773476898,
      "rd": 249
    },
    "best": {
      "rating": 1958,
      "date": 1741856198,
      "game": "https://www.chess.com/game/daily/113148106"
    },
    "record": {
      "win": 8,
      "loss": 0,
      "draw": 0,
      "time_per_move": 111543,
      "timeout_percent": 0
    }
  },
  "chess_rapid": {
    "last": {
      "rating": 2605,
      "date": 1773755329,
      "rd": 49
    },
    "best": {
      "rating": 2605,
      "date": 1766313971,
      "game": "https://www.chess.com/game/live/142764034780"
    },
    "record": {
      "win": 159,
      "loss": 33,
      "draw": 16
    }
  },
  "chess_bullet": {
    "last": {
      "rating": 2878,
      "date": 1771095563,
      "rd": 34
    },
    "best": {
      "rating": 2913,
      "date": 1771094386,
      "game": "https://www.chess.com/game/live/165403809457"
    },
    "record": {
      "win": 2261,
      "loss": 1553,
      "draw": 291
    }
  },
  "chess_blitz": {
    "last": {
      "rating": 2958,
      "date": 1776283814,
      "rd": 33
    },
    "best": {
      "rating": 3090,
      "date": 1768522127,
      "game": "https://www.chess.com/game/live/148333218304"
    },
    "record": {
      "win": 5325,
      "loss": 4494,
      "draw": 1512
    }
  },
  "tactics": {
    "highest": {
      "rating": 2887,
      "date": 1776592447
    },
    "lowest": {
      "rating": 2712,
      "date": 1765964217
    }
  },
  "puzzle_rush": {
    "best": {
      "total_attempts": 66,
      "score": 63
    }
  }
}