{
  "avatar": "https://images.chesscomfiles.com/uploads/v1/user/204077151.4ceb8f8e.200x200o.b5eef0079c52.jpg",
  "player_id": 204077151,
  "@id": "https://api.chess.com/pub/player/ddobravcan",
  "url": "https://www.chess.com/member/dDobravcan",
  "name": "Zlatko Lisjak",
  "username": "ddobravcan",
  "title": "FM",
  "followers": 11,
  "country": "https://api.chess.com/pub/country/HR",
  "location": "Varazdin",
  "last_online": 1776539078,
  "joined": 1667200079,
  "status": "premium",
  "is_streamer": false,
  "verified": false,
  "league": "Legend",
  "streaming_platforms": [],
  "chess_rapid": {
    "last": {
      "rating": 2168,
      "date": 1740987143,
      "rd": 46
    },
    "best": {
      "rating": 2216,
      "date": 1709538902,
      "game": "https://www.chess.com/game/live/103276856983"
    },
    "record": {
      "win": 10,
      "loss": 11,
      "draw": 0
    }
  },
  "chess_blitz": {
    "last": {
      "rating": 2164,
      "date": 1772134184,
      "rd": 24
    },
    "best": {
      "rating": 2294,
      "date": 1738937359,
      "game": "https://www.chess.com/game/live/131822454593"
    },
    "record": {
      "win": 2654,
      "loss": 2680,
      "draw": 248
    }
  },
  "tactics": {
    "highest": {
      "rating": 2332,
      "date": 1771167727
    },
    "lowest": {
      "rating": 2258,
      "date": 1767641195
    }
  },
  "puzzle_rush": {
    "best": {
      "total_attempts": 61,
      "score": 58
    }
  }
}