{
  "avatar": "https://images.chesscomfiles.com/uploads/v1/user/294076047.5239534b.200x200o.39201a7fd97d.jpg",
  "player_id": 294076047,
  "@id": "https://api.chess.com/pub/player/masterisback04",
  "url": "https://www.chess.com/member/Masterisback04",
  "name": "Jes\u00fas Manuel Vargas Pereda",
  "username": "masterisback04",
  "title": "CM",
  "followers": 31,
  "country": "https://api.chess.com/pub/country/MX",
  "location": "Ju\u00e1rez",
  "last_online": 1775478633,
  "joined": 1686949726,
  "status": "premium",
  "is_streamer": false,
  "verified": false,
  "league": "Silver",
  "streaming_platforms": [],
  "chess_rapid": {
    "last": {
      "rating": 2005,
      "date": 1774545579,
      "rd": 49
    },
    "best": {
      "rating": 2279,
      "date": 1687582201,
      "game": "https://www.chess.com/game/live/82092608391"
    },
    "record": {
      "win": 30,
      "loss": 47,
      "draw": 2
    }
  },
  "chess_bullet": {
    "last": {
      "rating": 1942,
      "date": 1745290044,
      "rd": 62
    },
    "best": {
      "rating": 2128,
      "date": 1707290022,
      "game": "https://www.chess.com/game/live/127935547933"
    },
    "record": {
      "win": 498,
      "loss": 553,
      "draw": 35
    }
  },
  "chess_blitz": {
    "last": {
      "rating": 2058,
      "date": 1774122268,
      "rd": 49
    },
    "best": {
      "rating": 2213,
      "date": 1726576618,
      "game": "https://www.chess.com/game/live/104621514153"
    },
    "record": {
      "win": 250,
      "loss": 410,
      "draw": 18
    }
  },
  "fide": 2006,
  "tactics": {
    "highest": {
      "rating": 2274,
      "date": 1772025288
    },
    "lowest": {
      "rating": 2041,
      "date": 1772387027
    }
  },
  "puzzle_rush": {
    "best": {
      "total_attempts": 43,
      "score": 41
    }
  }
}