{
  "avatar": "https://images.chesscomfiles.com/uploads/v1/user/32562480.0f231dc9.200x200o.6560dc112c46.jpg",
  "player_id": 32562480,
  "@id": "https://api.chess.com/pub/player/pandaguy4000",
  "url": "https://www.chess.com/member/Pandaguy4000",
  "name": "Filip Ochedzan",
  "username": "pandaguy4000",
  "title": "CM",
  "followers": 14,
  "country": "https://api.chess.com/pub/country/PL",
  "last_online": 1774374139,
  "joined": 1485009892,
  "status": "premium",
  "is_streamer": false,
  "verified": false,
  "league": "Crystal",
  "streaming_platforms": [],
  "chess_rapid": {
    "last": {
      "rating": 2184,
      "date": 1754255095,
      "rd": 48
    },
    "best": {
      "rating": 2193,
      "date": 1750685067,
      "game": "https://www.chess.com/game/live/148566509855"
    },
    "record": {
      "win": 637,
      "loss": 486,
      "draw": 63
    }
  },
  "chess_bullet": {
    "last": {
      "rating": 2500,
      "date": 1754255331,
      "rd": 59
    },
    "best": {
      "rating": 2517,
      "date": 1748102533,
      "game": "https://www.chess.com/game/live/133381184635"
    },
    "record": {
      "win": 141,
      "loss": 207,
      "draw": 21
    }
  },
  "chess_blitz": {
    "last": {
      "rating": 2407,
      "date": 1774371992,
      "rd": 71
    },
    "best": {
      "rating": 2466,
      "date": 1768926737,
      "game": "https://www.chess.com/game/live/163238228179"
    },
    "record": {
      "win": 368,
      "loss": 432,
      "draw": 38
    }
  },
  "fide": 2201,
  "tactics": {
    "highest": {
      "rating": 1920,
      "date": 1485009892
    },
    "lowest": {
      "rating": 1920,
      "date": 1485009892
    }
  },
  "puzzle_rush": {
    "best": {
      "total_attempts": 48,
      "score": 45
    }
  }
}