{
  "player_id": 350250599,
  "@id": "https://api.chess.com/pub/player/aural1011",
  "url": "https://www.chess.com/member/Aural1011",
  "name": "Laura Sofia Huayhuas Robles",
  "username": "aural1011",
  "title": "WCM",
  "followers": 1,
  "country": "https://api.chess.com/pub/country/PE",
  "location": "Callao",
  "last_online": 1774389637,
  "joined": 1710179566,
  "status": "premium",
  "is_streamer": false,
  "verified": false,
  "league": "Bronze",
  "streaming_platforms": [],
  "chess_rapid": {
    "last": {
      "rating": 2068,
      "date": 1754964162,
      "rd": 49
    },
    "best": {
      "rating": 2077,
      "date": 1716578723,
      "game": "https://www.chess.com/game/live/110316743925"
    },
    "record": {
      "win": 3,
      "loss": 1,
      "draw": 0
    }
  },
  "chess_bullet": {
    "last": {
      "rating": 1634,
      "date": 1710881455,
      "rd": 246
    },
    "record": {
      "win": 0,
      "loss": 1,
      "draw": 0
    }
  },
  "chess_blitz": {
    "last": {
      "rating": 2151,
      "date": 1774376445,
      "rd": 84
    },
    "best": {
      "rating": 2244,
      "date": 1774369017,
      "game": "https://www.chess.com/game/live/168077419553"
    },
    "record": {
      "win": 8,
      "loss": 43,
      "draw": 5
    }
  },
  "fide": 1801,
  "tactics": {
    "highest": {
      "rating": 400,
      "date": 1710179566
    },
    "lowest": {
      "rating": 400,
      "date": 1710179566
    }
  },
  "puzzle_rush": {
    "best": {
      "total_attempts": 39,
      "score": 37
    }
  }
}