{
  "avatar": "https://images.chesscomfiles.com/uploads/v1/user/376510417.a4195925.200x200o.69f0a2aac61c.jpg",
  "player_id": 376510417,
  "@id": "https://api.chess.com/pub/player/ebilski0106",
  "url": "https://www.chess.com/member/Ebilski0106",
  "name": "Yedil Kabylbek",
  "username": "ebilski0106",
  "title": "CM",
  "followers": 13,
  "country": "https://api.chess.com/pub/country/BE",
  "last_online": 1776595257,
  "joined": 1721540619,
  "status": "premium",
  "is_streamer": false,
  "verified": false,
  "league": "Legend",
  "streaming_platforms": [],
  "chess_rapid": {
    "last": {
      "rating": 2231,
      "date": 1765293685,
      "rd": 50
    },
    "best": {
      "rating": 2000,
      "date": 1763200639,
      "game": "https://www.chess.com/game/live/145536209028"
    },
    "record": {
      "win": 2,
      "loss": 0,
      "draw": 0
    }
  },
  "chess_bullet": {
    "last": {
      "rating": 2552,
      "date": 1768457819,
      "rd": 42
    },
    "best": {
      "rating": 2593,
      "date": 1758126777,
      "game": "https://www.chess.com/game/live/145508875964"
    },
    "record": {
      "win": 316,
      "loss": 218,
      "draw": 26
    }
  },
  "chess_blitz": {
    "last": {
      "rating": 2650,
      "date": 1776257950,
      "rd": 30
    },
    "best": {
      "rating": 2871,
      "date": 1772443131,
      "game": "https://www.chess.com/game/live/165403539046"
    },
    "record": {
      "win": 991,
      "loss": 642,
      "draw": 124
    }
  },
  "fide": 2231,
  "tactics": {
    "highest": {
      "rating": 2231,
      "date": 1765870090
    },
    "lowest": {
      "rating": 1845,
      "date": 1765870100
    }
  },
  "puzzle_rush": {
    "best": {
      "total_attempts": 49,
      "score": 46
    }
  }
}