{
  "player_id": 390288107,
  "@id": "https://api.chess.com/pub/player/flamingsword79",
  "url": "https://www.chess.com/member/Flamingsword79",
  "username": "flamingsword79",
  "title": "FM",
  "followers": 10,
  "country": "https://api.chess.com/pub/country/US",
  "last_online": 1776522266,
  "joined": 1726943767,
  "status": "premium",
  "is_streamer": false,
  "verified": false,
  "league": "Legend",
  "streaming_platforms": [],
  "chess_rapid": {
    "last": {
      "rating": 2084,
      "date": 1749738927,
      "rd": 49
    },
    "best": {
      "rating": 2084,
      "date": 1749738917,
      "game": "https://www.chess.com/game/live/122156320761"
    },
    "record": {
      "win": 1,
      "loss": 1,
      "draw": 0
    }
  },
  "chess_bullet": {
    "last": {
      "rating": 2512,
      "date": 1750171340,
      "rd": 43
    },
    "best": {
      "rating": 2536,
      "date": 1750170336,
      "game": "https://www.chess.com/game/live/139695827042"
    },
    "record": {
      "win": 8,
      "loss": 8,
      "draw": 1
    }
  },
  "chess_blitz": {
    "last": {
      "rating": 2366,
      "date": 1776347542,
      "rd": 19
    },
    "best": {
      "rating": 2539,
      "date": 1751772497,
      "game": "https://www.chess.com/game/live/166156463518"
    },
    "record": {
      "win": 1505,
      "loss": 1694,
      "draw": 166
    }
  },
  "fide": 0,
  "tactics": {
    "highest": {
      "rating": 1876,
      "date": 1726943767
    },
    "lowest": {
      "rating": 1876,
      "date": 1726943767
    }
  },
  "puzzle_rush": {
    "best": {
      "total_attempts": 36,
      "score": 35
    }
  }
}