{
  "player_id": 45485232,
  "@id": "https://api.chess.com/pub/player/elengajger",
  "url": "https://www.chess.com/member/ElenGajger",
  "name": "Milan Dobrijevic",
  "username": "elengajger",
  "title": "CM",
  "followers": 121,
  "country": "https://api.chess.com/pub/country/RS",
  "last_online": 1776521070,
  "joined": 1524248313,
  "status": "premium",
  "is_streamer": false,
  "verified": false,
  "league": "Legend",
  "streaming_platforms": [],
  "chess_bullet": {
    "last": {
      "rating": 2357,
      "date": 1764002405,
      "rd": 38
    },
    "best": {
      "rating": 2533,
      "date": 1756223463,
      "game": "https://www.chess.com/game/live/142112367192"
    },
    "record": {
      "win": 1400,
      "loss": 1140,
      "draw": 129
    }
  },
  "chess_blitz": {
    "last": {
      "rating": 2552,
      "date": 1776521059,
      "rd": 23
    },
    "best": {
      "rating": 2703,
      "date": 1773500650,
      "game": "https://www.chess.com/game/live/144811490262"
    },
    "record": {
      "win": 13775,
      "loss": 11351,
      "draw": 2271
    }
  },
  "fide": 0,
  "tactics": {
    "highest": {
      "rating": 2358,
      "date": 1759322478
    },
    "lowest": {
      "rating": 2069,
      "date": 1775380007
    }
  },
  "puzzle_rush": {
    "best": {
      "total_attempts": 32,
      "score": 29
    }
  }
}