{
  "avatar": "https://images.chesscomfiles.com/uploads/v1/user/46881544.f7fa5d55.200x200o.7f441ddefd5d.jpeg",
  "player_id": 46881544,
  "@id": "https://api.chess.com/pub/player/pawn_chainer",
  "url": "https://www.chess.com/member/pawn_chainer",
  "name": "Pavel Rozanov",
  "username": "pawn_chainer",
  "title": "FM",
  "followers": 1,
  "country": "https://api.chess.com/pub/country/RU",
  "last_online": 1776540413,
  "joined": 1528358183,
  "status": "premium",
  "is_streamer": false,
  "verified": false,
  "league": "Bronze",
  "streaming_platforms": [],
  "chess_blitz": {
    "last": {
      "rating": 2625,
      "date": 1776240114,
      "rd": 36
    },
    "best": {
      "rating": 2625,
      "date": 1776240114,
      "game": "https://www.chess.com/game/live/165772113868"
    },
    "record": {
      "win": 1570,
      "loss": 1307,
      "draw": 150
    }
  },
  "tactics": {
    "highest": {
      "rating": 1948,
      "date": 1528358183
    },
    "lowest": {
      "rating": 1948,
      "date": 1528358183
    }
  },
  "puzzle_rush": {
    "best": {
      "total_attempts": 51,
      "score": 48
    },
    "daily": {
      "total_attempts": 38,
      "score": 35
    }
  }
}