{
  "player_id": 6391187,
  "@id": "https://api.chess.com/pub/player/honzaceka",
  "url": "https://www.chess.com/member/honzaceka",
  "name": "Jan Vasek",
  "username": "honzaceka",
  "title": "NM",
  "followers": 169,
  "country": "https://api.chess.com/pub/country/CZ",
  "last_online": 1776598408,
  "joined": 1324978875,
  "status": "premium",
  "is_streamer": false,
  "verified": false,
  "league": "Legend",
  "streaming_platforms": [],
  "chess_rapid": {
    "last": {
      "rating": 2358,
      "date": 1774858799,
      "rd": 29
    },
    "best": {
      "rating": 2492,
      "date": 1772167000,
      "game": "https://www.chess.com/game/live/165284369102"
    },
    "record": {
      "win": 537,
      "loss": 374,
      "draw": 94
    }
  },
  "chess_bullet": {
    "last": {
      "rating": 1836,
      "date": 1691413031,
      "rd": 287
    },
    "record": {
      "win": 0,
      "loss": 1,
      "draw": 0
    }
  },
  "chess_blitz": {
    "last": {
      "rating": 2256,
      "date": 1776598400,
      "rd": 24
    },
    "best": {
      "rating": 2469,
      "date": 1767121654,
      "game": "https://www.chess.com/game/live/109870869005"
    },
    "record": {
      "win": 37707,
      "loss": 34455,
      "draw": 4063
    }
  },
  "fide": 2150,
  "tactics": {
    "highest": {
      "rating": 2356,
      "date": 1765527694
    },
    "lowest": {
      "rating": 2106,
      "date": 1768418988
    }
  },
  "puzzle_rush": {}
}