{
  "avatar": "https://images.chesscomfiles.com/uploads/v1/user/87083836.731620b6.200x200o.7f5cdb4b5475.png",
  "player_id": 87083836,
  "@id": "https://api.chess.com/pub/player/darkwhiteknight96",
  "url": "https://www.chess.com/member/darkwhiteknight96",
  "name": "Mauricio Hernandez",
  "username": "darkwhiteknight96",
  "title": "CM",
  "followers": 2,
  "country": "https://api.chess.com/pub/country/SV",
  "last_online": 1771979384,
  "joined": 1595175266,
  "status": "premium",
  "is_streamer": false,
  "verified": false,
  "league": "Bronze",
  "streaming_platforms": [],
  "chess_rapid": {
    "last": {
      "rating": 2060,
      "date": 1758256817,
      "rd": 48
    },
    "best": {
      "rating": 2068,
      "date": 1758256441,
      "game": "https://www.chess.com/game/live/5273853180"
    },
    "record": {
      "win": 6,
      "loss": 6,
      "draw": 0
    }
  },
  "chess_blitz": {
    "last": {
      "rating": 1891,
      "date": 1771613348,
      "rd": 41
    },
    "best": {
      "rating": 2233,
      "date": 1768163862,
      "game": "https://www.chess.com/game/live/147933147328"
    },
    "record": {
      "win": 60,
      "loss": 62,
      "draw": 3
    }
  },
  "tactics": {
    "highest": {
      "rating": 1192,
      "date": 1771977374
    },
    "lowest": {
      "rating": 497,
      "date": 1769645881
    }
  },
  "puzzle_rush": {}
}