{
  "avatar": "https://images.chesscomfiles.com/uploads/v1/user/88494518.5968038a.200x200o.7e07c610c615.jpg",
  "player_id": 88494518,
  "@id": "https://api.chess.com/pub/player/alivehula8",
  "url": "https://www.chess.com/member/AliveHula8",
  "name": "Luke Ye",
  "username": "alivehula8",
  "title": "NM",
  "followers": 42,
  "country": "https://api.chess.com/pub/country/US",
  "last_online": 1775994174,
  "joined": 1596743259,
  "status": "premium",
  "is_streamer": false,
  "verified": false,
  "league": "Elite",
  "streaming_platforms": [],
  "chess_daily": {
    "last": {
      "rating": 1751,
      "date": 1752682344,
      "rd": 302
    },
    "best": {
      "rating": 1751,
      "date": 1718188368,
      "game": "https://www.chess.com/game/daily/421703247"
    },
    "record": {
      "win": 5,
      "loss": 0,
      "draw": 0,
      "time_per_move": 62584,
      "timeout_percent": 0
    }
  },
  "chess_rapid": {
    "last": {
      "rating": 2380,
      "date": 1774444150,
      "rd": 49
    },
    "best": {
      "rating": 2380,
      "date": 1774444150,
      "game": "https://www.chess.com/game/live/146480751388"
    },
    "record": {
      "win": 167,
      "loss": 50,
      "draw": 31
    }
  },
  "chess_bullet": {
    "last": {
      "rating": 2408,
      "date": 1767655332,
      "rd": 43
    },
    "best": {
      "rating": 2473,
      "date": 1767646449,
      "game": "https://www.chess.com/game/live/147329786176"
    },
    "record": {
      "win": 549,
      "loss": 444,
      "draw": 58
    }
  },
  "chess_blitz": {
    "last": {
      "rating": 2339,
      "date": 1773448389,
      "rd": 64
    },
    "best": {
      "rating": 2452,
      "date": 1758809664,
      "game": "https://www.chess.com/game/live/142849849924"
    },
    "record": {
      "win": 322,
      "loss": 201,
      "draw": 41
    }
  },
  "tactics": {
    "highest": {
      "rating": 2624,
      "date": 1761881192
    },
    "lowest": {
      "rating": 2503,
      "date": 1766931144
    }
  },
  "puzzle_rush": {
    "best": {
      "total_attempts": 60,
      "score": 57
    }
  }
}