{
  "player_id": 89206656,
  "@id": "https://api.chess.com/pub/player/abd-2025",
  "url": "https://www.chess.com/member/Abd-2025",
  "name": "Abdou Ahmed Alem",
  "username": "abd-2025",
  "title": "CM",
  "followers": 93,
  "country": "https://api.chess.com/pub/country/PS",
  "location": "bhg",
  "last_online": 1776452864,
  "joined": 1597608156,
  "status": "premium",
  "is_streamer": false,
  "verified": false,
  "league": "Champion",
  "streaming_platforms": [],
  "chess_daily": {
    "last": {
      "rating": 869,
      "date": 1774612222,
      "rd": 221
    },
    "best": {
      "rating": 966,
      "date": 1769888497,
      "game": "https://www.chess.com/game/daily/911664141"
    },
    "record": {
      "win": 3,
      "loss": 5,
      "draw": 0,
      "time_per_move": 70252,
      "timeout_percent": 0
    }
  },
  "chess_rapid": {
    "last": {
      "rating": 2000,
      "date": 1759536038,
      "rd": 118
    },
    "best": {
      "rating": 2000,
      "date": 1759535946,
      "game": "https://www.chess.com/game/live/153848800307"
    },
    "record": {
      "win": 73,
      "loss": 31,
      "draw": 5
    }
  },
  "chess_bullet": {
    "last": {
      "rating": 2294,
      "date": 1774721218,
      "rd": 37
    },
    "best": {
      "rating": 2359,
      "date": 1771432927,
      "game": "https://www.chess.com/game/live/169032642151"
    },
    "record": {
      "win": 840,
      "loss": 1036,
      "draw": 124
    }
  },
  "chess_blitz": {
    "last": {
      "rating": 2310,
      "date": 1775930262,
      "rd": 45
    },
    "best": {
      "rating": 2392,
      "date": 1754004398,
      "game": "https://www.chess.com/game/live/132452395741"
    },
    "record": {
      "win": 731,
      "loss": 607,
      "draw": 74
    }
  },
  "fide": 1967,
  "tactics": {
    "highest": {
      "rating": 2325,
      "date": 1597608156
    },
    "lowest": {
      "rating": 2325,
      "date": 1597608156
    }
  },
  "puzzle_rush": {
    "best": {
      "total_attempts": 56,
      "score": 53
    }
  }
}